[


{ "en": "clean",       "fi": "puhdas",    "fr": "propre",    "es": "limpio",   "ko": "깨끗하다"},
{ "en": "dirty",       "fi": "likainen" , "fr": "sale",      "es": "sucio",   "ko": "더럽다"},

{ "en": "put",         "fi": "panna",     "fr": "placer, mettre",  "ko": " 두다" },
{ "en": "to give",     "fi": "antaa",     "fr": "donner",     "es": "dar",       "ko": "주다" },
{ "en": "to receive",  "fi": "saada",     "fr": "recevoir",   "es": "recibir",   "ko": "받다" },
{ "en": "to borrow",   "fi": "lainata, ottaa lainaksi",    "fr": "emprunter",  "ko": "빌리다" },
{ "en": "to lend",        "ko": "빌려주다",          "fi": "lainata, antaa lainaksi",    "fr": "prêter" },
{ "en": "present",        "ko": "선물",          "fi": "lahja",    "fr": "cadeau" },



{ "en": "delivery",      "fi": "toimitus",    "fr": "livraison",        "ko": "배달" },
{ "en": "deliver",       "ko": "배달하다",       "fi": "toimittaa",    "fr": "livrer" },


{ "en": "joyful",        "ko": "즐겁다",          "fi": "iloinen",    "fr": "joyeux" },

{ "en": "to open",    "ko": "열다",       "fi": "avata",    "fr": "ouvrir" },
{ "en": "open",    "ko": "열다",       "fi": "auki",    "fr": "ouvert" },
{ "en": "to close",    "ko": "닫다",       "fi": "sulkea",    "fr": "fermer" },
{ "en": "closed",    "ko": "",       "fi": "suljettu, kiinni",    "fr": "fermé" },

{ "en": "difficult",       "ko": "어렵다",       "fi": "vaikea",    "fr": "difficile" },
{ "en": "easy",       "fi": "helppo",    "fr": "facile",   "es": "fácil",  "ko": "쉽다" },


{ "en": "important",        "ko": "중요하다",          "fi": "tärkeä",    "fr": "important" },
{ "en": "popular",        "ko": "인기 있는, 유명한",          "fi": "suosittu",    "fr": "populaire" },
{ "en": "popularity",        "ko": "인기",          "fi": "suosio",    "fr": "popularité" },
{ "en": "favorite",        "ko": "",          "fi": "suosikki",    "fr": "favori, préféré" },

{ "en": "nice",        "ko": "",          "fi": "kiva, mukava",       "fr": "agréable" },
{ "en": "pleasant",    "ko": "",          "fi": "miellyttävä, mukava","fr": "agréable" },
{ "en": "comfortable", "ko": "",            "fi": "mukava",             "fr": "confortable" },


{ "en": "useful",       "ko": "",          "fi": "hyödyllinen", "fr": "utile" },
{ "en": "handy",        "ko": "",          "fi": "kätevä",      "fr": "maniable, pratique" },

{ "en": "rise",        "ko": "오르다",          "fi": "nousta",    "fr": "augmenter" },
{ "en": "significantly",        "ko": "크게",          "fi": "merkittävästi",    "fr": "significativement" },
{ "en": "advertisment",        "ko": "광고",          "fi": "mainos",    "fr": "publicité" },


{ "en": "same",           "fi": "samanlainen",    "fr": "même",   "es": "mismo",  "ko": "같다" },
{ "en": "similar",        "fi": "samanlainen",    "fr": "similaire, semblable", "es": "parecido (a), similar",  "ko": "비슷하다" },
{ "en": "different",        "ko": "다르다, 다른",          "fi": "eri, erilainen",    "fr": "différent, autre" },
{ "en": "to resemble",        "ko": "닮다",          "fi": "muistuttaa",    "fr": "ressembler à" },
{ "en": "to compare",        "ko": "비교하다, (~에) 필적하다",          "fi": "verrata (part + ill), vertailla",    "fr": "comparer" },
{ "en": "comparison",        "ko": "비교",          "fi": "vertailu",    "fr": "comparaison" },

{ "en": "relation",             "ko": "관계",       "fi": "suhde",    "fr":"relation, rapport"},
{ "en": "relative",             "ko": "상대적인",   "fi": "suhteellinen",    "fr":"relatif"},
{ "en": "ratio, proportion",    "ko": "비율",       "fi": "suhde",    "fr": "rapport, ratio" },


{ "en": "other",        "ko": "다른",     "fi": "muu",           "fr": "autre" },
{ "en": "only",         "ko": "만",       "fi": "vain",          "fr": "seulement" },



{ "en": "become",        "ko": "되다",    "fi": "tulla",          "fr": "devenir" },
{ "en": "beginning (noun)", "ko": "처음", "fi": "alku",           "fr": "début" },

{ "en": "last",        "ko": "마지막",          "fi": "viime",    "fr": "dernier" },


{ "en": "to help",     "fi": "auttaa",      "fr": "aider",         "es": "ayudar",      "ko": "돕다" },
{ "en": "help",        "fi": "apu, ohje",   "fr": "aide, secours", "es": "(la) ayuda",  "ko": "도움" },

{ "en": "to lie",      "fi": "valehdella",  "fr": "mentir",        "es": "mentir",      "ko": "거짓말하다" },
{ "en": "lie",         "fi": "valhe",       "fr": "mensonge",      "es": "mentira",     "ko": "거짓말" },
{ "en": "a secret",    "fi": "salaisuus",   "fr": "secret",        "es": "(el) secreto","ko": "비밀"},
{ "en": "secret",      "fi": "salainen",    "fr": "secret",        "es": "secreto",     "ko": "비밀"},

{ "en": "fact",         "ko": "사실",       "fi": "tosiasia",          "fr": "fait, vérité" },
{ "en": "joke",         "ko": "농담",       "fi": "vitsi",          "fr": "blague" },

{ "en": "meaning",         "ko": "의미, 뜻",       "fi": "merkitys, tarkoitus",          "fr": "sens, signification" },
{ "en": "purpose",         "ko": "목적",       "fi": "tarkoitus",          "fr": "but, intention" },
    
{ "en": "to consider",         "ko": "고려하다",       "fi": "harkita",          "fr": "envisager, considérer" },
{ "en": "believe",         "fi": "uskoa (siihen)",    "fr": "croire",  "es": "creer",  "ko": "믿다" },
{ "en": "to expect",       "ko": "예상하다, 기대하다",       "fi": "odottaa",    "fr": "attendre" },
{ "en": "to intend",       "ko": "",       "fi": "aikoa",    "fr": "avoir l'intention" },
{ "en": "to hope",       "ko": "희망하다",       "fi": "toivoa",    "fr": "espérer" },
{ "en": "hope",       "ko": "희망",       "fi": "toivo",    "fr": "espoir" },




{ "en": "to forbid",       "fi": "kieltää",    "fr": "interdire",   "es": "prohibir", "ko": "금하다" },

{ "en": "to be used, be utilized",       "ko": "쓰이다",       "fi": "",    "fr": "" },
{ "en": "event",           "fi": "tapahtuma",  "fr": "événement",   "ko": "행사" },
{ "en": "situation",       "fi": "tilanne",    "fr": "situation",   "es": "(la) situación",      "ko": "?" },
{ "en": "knowledge",       "fi": "tieto",      "fr": "connaissance","es": "(el) conocimiento",   "ko": "지식" },

  
{ "en": "empty",       "ko": "비다",       "fi": "tyhjä",    "fr": "vide" },
{ "en": "vacant",       "ko": "비다",       "fi": "vapaa",    "fr": "vacant" }

]
        