[


{ "en": "chest",     "fi": "rinta",    "fr": "poitrine",    "hu": "mellkas", "ko": "가슴"},
{ "en": "heart",     "fi": "sydän",    "fr": "cœur",        "hu": "szív",    "ko": "심장 (heart + organ)"  },
{ "en": "leg",       "fi": "jalka",    "fr": "jambe",       "hu": "láb",     "ko": "다리"    },
{ "en": "foot",      "fi": "jalka",    "fr": "pied",        "hu": "láb",     "ko": "발"      },

{ "en": "head",      "fi": "pää",      "fr": "tête",        "hu": "fej",     "ko": "머리" },
{ "en": "face",      "fi": "silmä",    "fr": "œil",         "hu": "arc",     "ko": "얼굴" },
{ "en": "eye",       "fi": "kasvot",   "fr": "face, visage","hu": "szem",    "ko": "눈"   },
{ "en": "brain",     "fi": "aivot",    "fr": "cerveau",     "hu": "agy",     "ko": "뇌"   },
{ "en": "neck",      "fi": "kaula",    "fr": "cou",         "hu": "nyak",    "ko": "목"   },
{ "en": "tongue",    "fi": "kieli",    "fr": "langue",      "hu": "nyelv",   "ko": "혀"   },
{ "en": "ear",       "fi": "korva",    "fr": "oreille",     "hu": "fül",     "ko": "귀"   },
{ "en": "body",      "fi": "keho",     "fr": "corps",       "hu": "",     "ko": "몸"   },
{ "en": "hand",      "fi": "käsi",     "fr": "main",        "hu": "",     "ko": "손"   },
{ "en": "left",      "fi": "",    "fr": "",  "ko": "왼"       },
{ "en": "right",     "fi": "",    "fr": "",  "ko": "오른"     },
{ "en": "finger",    "fi": "sormi",    "fr": "doigt",  "ko": "손가락"     },
{ "en": "fingerprint",       "ko": "지문",         "fi": "sormenjälki",    "fr": "empreinte digitale" },


{ "en": "skin",       "ko": "피부",         "fi": "iho",    "fr": "peau" },
{ "en": "hair",       "ko": "머리",         "fi": "tukka, hiukset",    "fr": "cheveux" },

{ "en": "to touch",       "ko": "대다",         "fi": "koskea",    "fr": "toucher" },
{ "en": "to raise",       "ko": "들다",         "fi": "",    "fr": "" },


{ "en": "a bone",    "ko": "뼈",    "fi": "luu" , "fr":"os"},
{ "en": "blood",    "ko": "피",    "fi": "veri" , "fr":"sang"},
{ "en": "lung",    "ko": "폐",    "fi": "keuhko" , "fr":"poumon"},

{ "en": "female",       "ko": "여성",         "fi": "nainen",    "fr": "femelle" },

{ "en": "liver",       "ko": "간",       "fi": "maksa",    "fr": "foie" },
{ "en": "eyebrow",       "ko": "눈썹",       "fi": "kulmakarva",    "fr": "sourcil" },
{ "en": "nail",       "ko": "손톱",       "fi": "kynsi",    "fr": "ongle" },
{ "en": "ankle",       "ko": "발목",       "fi": "nilkka",    "fr": "cheville" },
{ "en": "hip",       "ko": "엉덩이",       "fi": "lonkka, lanne ",    "fr": "hanche" },
{ "en": "cheek",       "ko": "볼",         "fi": "poski",    "fr": "joue" },
{ "en": "chin",       "ko": "턱",         "fi": "leuka",    "fr": "menton" },
{ "en": "jaw",       "ko": "턱",         "fi": "leuka",    "fr": "mâchoire" },
{ "en": "shoulder",       "ko": "어깨",         "fi": "olkapää",    "fr": "épaule" },
{ "en": "elbow",       "ko": "팔꿈치",         "fi": "kyynärpää",    "fr": "coude" },

{ "en": "mentality",       "ko": "심리 (heart + principle)",         "fi": "mentaliteetti, mielenlaatu",    "fr": "mentalité" },
{ "en": "psychology",       "ko": "심리학 (heart + principle + study)",         "fi": "psykologia, sielutiede",    "fr": "psychologie" }

]